exdimred.py
exdimred-0.0.3.dist-info/LICENSE
exdimred-0.0.3.dist-info/METADATA
exdimred-0.0.3.dist-info/WHEEL
exdimred-0.0.3.dist-info/top_level.txt
exdimred-0.0.3.dist-info/RECORD
