Metadata-Version: 2.1
Name: exdimred
Version: 0.0.3
Summary: Toybox for intuitive evaluation of dimensionality reduction
Author: Alex Davies
Classifier: Programming Language :: Python :: 3
Classifier: License :: OSI Approved :: GNU General Public License v3 (GPLv3)
Classifier: Operating System :: OS Independent
Requires-Python: >=3.6
License-File: LICENSE
Requires-Dist: numpy
Requires-Dist: matplotlib
Requires-Dist: scikit-learn
Requires-Dist: umap-learn
Requires-Dist: tqdm
